misaem/__init__.py
misaem/misaem.py
misaem/utils.py
misaem-1.0.0.dist-info/METADATA
misaem-1.0.0.dist-info/WHEEL
misaem-1.0.0.dist-info/licenses/LICENSE
misaem-1.0.0.dist-info/RECORD
