Metadata-Version: 2.4
Name: misaem
Version: 1.0.0
Summary: A logistic regression model with missing data handling using the SAEM algorithm.
Project-URL: Homepage, https://github.com/ChristopheMuller/misaem_python
Project-URL: Issues, https://github.com/ChristopheMuller/misaem_python/issues
Author-email: Christophe Muller <mullerchristophe21@gmail.com>
License-File: LICENSE
Classifier: Development Status :: 3 - Alpha
Classifier: Intended Audience :: Science/Research
Classifier: License :: OSI Approved :: MIT License
Classifier: Operating System :: OS Independent
Classifier: Programming Language :: Python :: 3
Classifier: Programming Language :: Python :: 3.9
Classifier: Programming Language :: Python :: 3.10
Classifier: Programming Language :: Python :: 3.11
Classifier: Programming Language :: Python :: 3.12
Classifier: Topic :: Scientific/Engineering :: Artificial Intelligence
Classifier: Topic :: Scientific/Engineering :: Information Analysis
Classifier: Topic :: Scientific/Engineering :: Mathematics
Requires-Python: >=3.9
Requires-Dist: numpy>=1.20.0
Requires-Dist: scikit-learn>=1.5
Requires-Dist: tqdm>=4.0
Provides-Extra: dev
Requires-Dist: black; extra == 'dev'
Requires-Dist: flake8; extra == 'dev'
Requires-Dist: pytest>=7.0; extra == 'dev'
